jira/__init__.py
jira/client.py
jira/config.py
jira/exceptions.py
jira/jirashell.py
jira/py.typed
jira/resilientsession.py
jira/resources.py
jira/utils/LICENSE
jira/utils/__init__.py
tmp_jira_with_fix_template_name-1.0.0.dist-info/AUTHORS.rst
tmp_jira_with_fix_template_name-1.0.0.dist-info/LICENSE
tmp_jira_with_fix_template_name-1.0.0.dist-info/METADATA
tmp_jira_with_fix_template_name-1.0.0.dist-info/WHEEL
tmp_jira_with_fix_template_name-1.0.0.dist-info/entry_points.txt
tmp_jira_with_fix_template_name-1.0.0.dist-info/top_level.txt
tmp_jira_with_fix_template_name-1.0.0.dist-info/RECORD
